setup.py
pyrandom/__init__.py
pyrandom/pyrandom.py
pyrandom.egg-info/PKG-INFO
pyrandom.egg-info/SOURCES.txt
pyrandom.egg-info/dependency_links.txt
pyrandom.egg-info/requires.txt
pyrandom.egg-info/top_level.txt