Metadata-Version: 1.0
Name: pyrandom
Version: 0.0.1
Summary: a convenient Python lib for random.org 
Home-page: https://github.com/j178/pyrandom
Author: john jiang
Author-email: nigelchiang@outlook.com
License: MIT
Keywords: random,random.org
Platform: UNKNOWN
